fizzbuzz/__init__.py
fizzbuzz/fizzbuzz.py
fizzbuzz_a_a_r_2-0.1.0.dist-info/METADATA
fizzbuzz_a_a_r_2-0.1.0.dist-info/WHEEL
fizzbuzz_a_a_r_2-0.1.0.dist-info/RECORD
