Metadata-Version: 2.1
Name: fizzbuzz-a-a-r-2
Version: 0.1.0
Summary: Setting up CI project
Author: augustin-marie
Author-email: a.marie189@laposte.net
Requires-Python: >3.9
Classifier: Programming Language :: Python :: 3
Classifier: Programming Language :: Python :: 3.10
Classifier: Programming Language :: Python :: 3.11
Requires-Dist: flake8 (>=6.0.0,<7.0.0)
Requires-Dist: setuptools (==57.2.0)
